lookup_license/__init__.py
lookup_license/__main__.py
lookup_license/cache.py
lookup_license/config.py
lookup_license/format.py
lookup_license/license_db.py
lookup_license/ll_shell.py
lookup_license/lookuplicense.py
lookup_license/retrieve.py
lookup_license/utils.py
lookup_license/data/url-fixes.json
lookup_license/lookupurl/clearlydefined.py
lookup_license/lookupurl/factory.py
lookup_license/lookupurl/fixes.py
lookup_license/lookupurl/gem.py
lookup_license/lookupurl/gitrepo.py
lookup_license/lookupurl/go.py
lookup_license/lookupurl/license_provider.py
lookup_license/lookupurl/license_providers.py
lookup_license/lookupurl/lookupurl.py
lookup_license/lookupurl/maven.py
lookup_license/lookupurl/purl.py
lookup_license/lookupurl/purl2cd.py
lookup_license/lookupurl/purldb.py
lookup_license/lookupurl/pypi.py
lookup_license/lookupurl/swift.py
lookup_license/lookupurl/url.py
lookup_license-0.1.30.dist-info/GPL-3.0-or-later.txt
lookup_license-0.1.30.dist-info/METADATA
lookup_license-0.1.30.dist-info/WHEEL
lookup_license-0.1.30.dist-info/entry_points.txt
lookup_license-0.1.30.dist-info/top_level.txt
lookup_license-0.1.30.dist-info/RECORD
