Metadata-Version: 2.1
Name: lookup-license
Version: 0.1.30
Summary: Python tool to identify license from license text, urls, license names and package names.
Home-page: https://github.com/hesa/lookup-license
Author: Henrik Sanklef
Author-email: hesa@sandklef.com
Classifier: Development Status :: 4 - Beta
Classifier: Environment :: Console
Classifier: Intended Audience :: Developers
Classifier: Intended Audience :: Legal Industry
Classifier: License :: OSI Approved :: GNU General Public License v3 or later (GPLv3+)
Classifier: Natural Language :: English
Classifier: Operating System :: POSIX :: Linux
Classifier: Programming Language :: Python :: 3 :: Only
Classifier: Programming Language :: Python :: 3.6
Classifier: Programming Language :: Python :: 3.7
Classifier: Programming Language :: Python :: 3.8
Classifier: Programming Language :: Python :: 3.9
Classifier: Programming Language :: Python :: 3.10
Classifier: Programming Language :: Python :: 3.11
Classifier: Programming Language :: Python :: 3.12
Classifier: Programming Language :: Python :: 3
Classifier: Topic :: Software Development :: Quality Assurance
Requires-Python: >=3.6
License-File: LICENSES/GPL-3.0-or-later.txt
Requires-Dist: appdirs
Requires-Dist: cachetools
Requires-Dist: diskcache
Requires-Dist: foss-flame
Requires-Dist: license-expression
Requires-Dist: packageurl-python
Requires-Dist: python-magic
Requires-Dist: requests ==2.28.1
Requires-Dist: scancode-toolkit
Requires-Dist: xmltodict
Provides-Extra: dev
Requires-Dist: bump2version ~=1.0 ; extra == 'dev'
Requires-Dist: flake8 ~=5.0 ; extra == 'dev'
Requires-Dist: pytest ; extra == 'dev'
Requires-Dist: reuse ; extra == 'dev'
Requires-Dist: setuptools ; extra == 'dev'
Requires-Dist: twine ; extra == 'dev'
